{
  "CNCF": { "label": "CNCF", "color": "#326CE5" },
  "LF AI": { "label": "LF AI & Data", "color": "#0079C1" },
  "LF AI & Data": { "label": "LF AI & Data", "color": "#0079C1" },
  "LF Edge": { "label": "LF Edge", "color": "#00A3E0" },
  "LF Networking": { "label": "LF Networking", "color": "#00629B" },
  "Hyperledger": { "label": "Hyperledger", "color": "#2F3134" },
  "OpenSSF": { "label": "OpenSSF", "color": "#3DA639" },
  "CHAOSS": { "label": "CHAOSS", "color": "#FF6600" },
  "Linux Kernel": { "label": "Linux Foundation", "color": "#003366" },
  "Linux kernel": { "label": "Linux Foundation", "color": "#003366" },
  "Open Mainframe": { "label": "Open Mainframe Project", "color": "#006699" },
  "Open Mainframe Project": { "label": "Open Mainframe Project", "color": "#006699" },
  "OpenHPC": { "label": "OpenHPC", "color": "#0071BD" },
  "GraphQL": { "label": "GraphQL Foundation", "color": "#E535AB" },
  "Zephyr": { "label": "Zephyr Project", "color": "#5B2D8E" },
  "RISC-V": { "label": "RISC-V", "color": "#283750" },
  "Kyverno": { "label": "CNCF", "color": "#326CE5" },
  "Kubernetes": { "label": "CNCF", "color": "#326CE5" },
  "ELISA": { "label": "ELISA", "color": "#003366" },
  "LFX": { "label": "Linux Foundation", "color": "#003366" }
}
